pdftl/__init__.py
pdftl/__main__.py
pdftl/_version.py
pdftl/api.py
pdftl/api.pyi
pdftl/exceptions.py
pdftl/fluent.py
pdftl/fluent.pyi
pdftl/py.typed
pdftl/registry_init.py
pdftl/cli/__init__.py
pdftl/cli/console.py
pdftl/cli/constants.py
pdftl/cli/help.py
pdftl/cli/help_data.py
pdftl/cli/main.py
pdftl/cli/parser.py
pdftl/cli/pipeline.py
pdftl/cli/whoami.py
pdftl/core/__init__.py
pdftl/core/constants.py
pdftl/core/executor.py
pdftl/core/registry.py
pdftl/core/types.py
pdftl/info/info_types.py
pdftl/info/output_info.py
pdftl/info/parse_dump.py
pdftl/info/read_info.py
pdftl/info/set_info.py
pdftl/operations/__init__.py
pdftl/operations/add_text.py
pdftl/operations/attachments.py
pdftl/operations/burst.py
pdftl/operations/cat.py
pdftl/operations/chop.py
pdftl/operations/crop.py
pdftl/operations/delete.py
pdftl/operations/delete_annots.py
pdftl/operations/dump_annots.py
pdftl/operations/dump_data.py
pdftl/operations/dump_data_fields.py
pdftl/operations/dump_dests.py
pdftl/operations/dump_layers.py
pdftl/operations/dump_signatures.py
pdftl/operations/dump_text.py
pdftl/operations/fill_form.py
pdftl/operations/filter.py
pdftl/operations/generate_fdf.py
pdftl/operations/inject.py
pdftl/operations/insert.py
pdftl/operations/modify_annots.py
pdftl/operations/move.py
pdftl/operations/normalize.py
pdftl/operations/optimize_images.py
pdftl/operations/overlay.py
pdftl/operations/place.py
pdftl/operations/render.py
pdftl/operations/replace.py
pdftl/operations/rotate.py
pdftl/operations/shuffle.py
pdftl/operations/update_info.py
pdftl/operations/helpers/crop_fit.py
pdftl/operations/helpers/text_drawer.py
pdftl/operations/parsers/add_text_parser.py
pdftl/operations/parsers/chop_parser.py
pdftl/operations/parsers/crop_parser.py
pdftl/operations/parsers/inject_parser.py
pdftl/operations/parsers/insert_parser.py
pdftl/operations/parsers/modify_annots_parser.py
pdftl/operations/parsers/move_parser.py
pdftl/operations/parsers/place_parser.py
pdftl-0.7.0.dist-info/licenses/LICENSE
pdftl-0.7.0.dist-info/licenses/NOTICE.md
pdftl-0.7.0.dist-info/METADATA
pdftl-0.7.0.dist-info/WHEEL
pdftl-0.7.0.dist-info/entry_points.txt
pdftl-0.7.0.dist-info/top_level.txt
pdftl-0.7.0.dist-info/RECORD
