Metadata-Version: 2.4
Name: pdftl
Version: 0.7.0
Summary: A capable CLI tool for PDF manipulation inspired by pdftk.
Author-email: The pdftl developers <ether-jet-emerald@duck.com>
License-Expression: MPL-2.0
Project-URL: Homepage, https://github.com/pdftl/pdftl
Project-URL: Issues, https://github.com/pdftl/pdftl/issues
Project-URL: Repository, https://github.com/pdftl/pdftl
Project-URL: Documentation, https://pdftl.readthedocs.io
Project-URL: Changelog, https://github.com/pdftl/pdftl/blob/main/CHANGELOG.md
Keywords: pdf,pdftk,pdftl,cli,manipulation,automation
Classifier: Development Status :: 3 - Alpha
Classifier: Environment :: Console
Classifier: Programming Language :: Python :: 3
Classifier: Programming Language :: Python :: 3.10
Classifier: Programming Language :: Python :: 3.11
Classifier: Programming Language :: Python :: 3.12
Classifier: Programming Language :: Python :: 3.13
Classifier: Operating System :: OS Independent
Classifier: Topic :: Utilities
Classifier: Topic :: Text Processing
Requires-Python: >=3.10
License-File: LICENSE
License-File: NOTICE.md
Requires-Dist: pikepdf>=10.0.2
Requires-Dist: rich
Provides-Extra: add-text
Requires-Dist: reportlab; extra == "add-text"
Provides-Extra: crop-visible
Requires-Dist: pypdfium2; extra == "crop-visible"
Provides-Extra: dump-text
Requires-Dist: pypdfium2; extra == "dump-text"
Provides-Extra: flatten
Requires-Dist: pypdfium2; extra == "flatten"
Provides-Extra: optimize-images
Requires-Dist: ocrmypdf; extra == "optimize-images"
Provides-Extra: signing
Requires-Dist: pyhanko; extra == "signing"
Provides-Extra: extras
Requires-Dist: pdftl[add-text]; extra == "extras"
Requires-Dist: pdftl[crop-visible]; extra == "extras"
Requires-Dist: pdftl[dump-text]; extra == "extras"
Requires-Dist: pdftl[flatten]; extra == "extras"
Requires-Dist: pdftl[optimize-images]; extra == "extras"
Requires-Dist: pdftl[signing]; extra == "extras"
Provides-Extra: full
Requires-Dist: pdftl[extras]; extra == "full"
Provides-Extra: docs
Requires-Dist: sphinx>=7.0; extra == "docs"
Requires-Dist: sphinx-rtd-theme; extra == "docs"
Requires-Dist: myst-parser; extra == "docs"
Provides-Extra: dev
Requires-Dist: pytest; extra == "dev"
Requires-Dist: pytest-xdist; extra == "dev"
Requires-Dist: pytest-mock; extra == "dev"
Requires-Dist: pytest-cov; extra == "dev"
Requires-Dist: black; extra == "dev"
Requires-Dist: isort; extra == "dev"
Requires-Dist: ruff; extra == "dev"
Requires-Dist: toml; python_version < "3.11.0" and extra == "dev"
Requires-Dist: hypothesis; extra == "dev"
Requires-Dist: PyMuPDF; extra == "dev"
Requires-Dist: reportlab; extra == "dev"
Requires-Dist: mypy; extra == "dev"
Requires-Dist: cryptography; extra == "dev"
Requires-Dist: types-setuptools; extra == "dev"
Requires-Dist: pdftl[full]; extra == "dev"
Provides-Extra: dev-all
Requires-Dist: pdftl[dev]; extra == "dev-all"
Requires-Dist: pdftl[docs]; extra == "dev-all"
Dynamic: license-file
